{
    "id": "",
    "timestamp": 1633400601387,
    "productos": {
        "1": { "id": "5b96d092-3eb7-4a3e-a8a5-eb9d1b4ffff0", "timestamp": 1633399619913, "nombre": "Juego de mesa T.E.G. Tradicional", "descripcion": "Producto 1", "codigo": "JUE-01", "foto": "https://http2.mlstatic.com/D_NQ_NP_659090-MLA44676313817_012021-O.webp", "precio": 3850.50, "stock": 6 },
        "2": { "id": "d69083de-1bcd-4133-920c-6f9bace21d23", "timestamp": 1633399731538, "nombre": "Dungeon And Dragons 5e Monster Manual D&d Dnd 5ta Edición", "descripcion": "Producto 2", "codigo": "JUE-02", "foto": "https://http2.mlstatic.com/D_NQ_NP_726931-MLA45539678600_042021-O.webp", "precio": 11275, "stock": 2 }
    }
}